mrmime.py
mrmime-0.0.1.dist-info/LICENSE
mrmime-0.0.1.dist-info/WHEEL
mrmime-0.0.1.dist-info/METADATA
mrmime-0.0.1.dist-info/RECORD
