Metadata-Version: 2.1
Name: mrmime
Version: 0.0.1
Summary: A streaming mime parser
Home-page: https://git.sr.ht/~nhoad/mrmime
License: MIT
Author: Nathan Hoad
Author-email: nathan@hoad.io
Requires-Python: >=3.9,<4.0
Classifier: License :: OSI Approved :: MIT License
Classifier: Programming Language :: Python :: 3
Classifier: Programming Language :: Python :: 3.9
Requires-Dist: Werkzeug (>=2.0.1,<3.0.0)
Project-URL: Repository, https://git.sr.ht/~nhoad/mrmime
